fleet_control/__init__.py
fleet_control/fct.py
fleet_control/logging_config.py
fleet_control/resources/classes.py
fleet_control/resources/commands.py
fleet_control/utils/python_utils.py
fleet_control/utils/utils.py
fct_kiwi-1.16.0.dist-info/METADATA
fct_kiwi-1.16.0.dist-info/WHEEL
fct_kiwi-1.16.0.dist-info/entry_points.txt
fct_kiwi-1.16.0.dist-info/RECORD
