Metadata-Version: 2.4
Name: fct-kiwi
Version: 1.16.0
Summary: Balena fleet management
License: MIT
Keywords: balena,fleet control
Author: Juan Pablo Castillo
Author-email: jpc.2@outlook.com
Requires-Python: >=3.10,<4.0
Classifier: License :: OSI Approved :: MIT License
Classifier: Programming Language :: Python :: 3
Classifier: Programming Language :: Python :: 3.10
Classifier: Programming Language :: Python :: 3.11
Classifier: Programming Language :: Python :: 3.12
Classifier: Programming Language :: Python :: 3.13
Classifier: Programming Language :: Python :: 3.14
Requires-Dist: balena-sdk (>=15.1.2,<16.0.0)
Requires-Dist: click (>=8.1.8,<9.0.0)
Requires-Dist: deepdiff (>=8.6.0,<9.0.0)
Requires-Dist: google-auth (>=2.38.0,<3.0.0)
Requires-Dist: google-cloud-tasks (>=2.19.1,<3.0.0)
Requires-Dist: gspread (>=6.2.0,<7.0.0)
Requires-Dist: python-dotenv (>=1.1.0,<2.0.0)
Requires-Dist: pytz (>=2025.1,<2026.0)
Requires-Dist: pyyaml (>=6.0.2,<7.0.0)
Requires-Dist: requests (>=2.32.3,<3.0.0)
Project-URL: Repository, https://github.com/gokiwibot/fct-package
